CHANGES.rst
LICENSE
MANIFEST.in
README.rst
flask_basicauth.py
setup.py
test_basicauth.py
Flask_BasicAuth.egg-info/SOURCES.txt
docs/Makefile
docs/conf.py
docs/index.rst
docs/_themes/.gitignore
docs/_themes/LICENSE
docs/_themes/README
docs/_themes/flask_theme_support.py
docs/_themes/flask/layout.html
docs/_themes/flask/relations.html
docs/_themes/flask/theme.conf
docs/_themes/flask/static/flasky.css_t
docs/_themes/flask/static/small_flask.css
docs/_themes/flask_small/layout.html
docs/_themes/flask_small/theme.conf
docs/_themes/flask_small/static/flasky.css_t
flask_basicauth.egg-info/PKG-INFO
flask_basicauth.egg-info/SOURCES.txt
flask_basicauth.egg-info/dependency_links.txt
flask_basicauth.egg-info/not-zip-safe
flask_basicauth.egg-info/requires.txt
flask_basicauth.egg-info/top_level.txt