Metadata-Version: 1.1
Name: Flask-BasicAuth
Version: 0.1.1
Summary: HTTP basic access authentication for Flask.
Home-page: https://github.com/jpvanhal/flask-basicauth
Author: Janne Vanhala
Author-email: janne.vanhala@gmail.com
License: BSD
Platform: any
Classifier: Environment :: Web Environment
Classifier: Intended Audience :: Developers
Classifier: License :: OSI Approved :: BSD License
Classifier: Operating System :: OS Independent
Classifier: Programming Language :: Python
Classifier: Topic :: Internet :: WWW/HTTP :: Dynamic Content
Classifier: Topic :: Software Development :: Libraries :: Python Modules
